CHANGELOG.txt
LICENCE.txt
MANIFEST.in
README.txt
setup.py
savagediscord/__init__.py
savagediscord.egg-info/PKG-INFO
savagediscord.egg-info/SOURCES.txt
savagediscord.egg-info/dependency_links.txt
savagediscord.egg-info/requires.txt
savagediscord.egg-info/top_level.txt