Metadata-Version: 1.1
Name: savagediscord
Version: 0.0.2
Summary: For more info, go to: https://github.com/SavageMusicYT/savagediscord
Home-page: https://github.com/SavageMusicYT/savagediscord
Author: Savage Music
Author-email: support@savagesmusic.com
License: MIT
Keywords: discord
Platform: UNKNOWN
Classifier: Development Status :: 1 - Planning
Classifier: Intended Audience :: Developers
Classifier: Operating System :: Microsoft :: Windows :: Windows 10
Classifier: License :: OSI Approved :: MIT License
Classifier: Programming Language :: Python :: 3
